[
  {
    "description": "",
    "elements": [
      {
        "description": "",
        "id": "getting-products-count-functionality;check-if-products-are-available-on-the-products-page",
        "keyword": "Scenario",
        "line": 5,
        "name": "Check if products are available on the products page",
        "steps": [
          {
            "keyword": "Before",
            "hidden": true,
            "result": {
              "status": "passed",
              "duration": 1942251500
            }
          },
          {
            "arguments": [],
            "keyword": "When ",
            "line": 6,
            "name": "I navigate to the products page",
            "match": {
              "location": "src\\steps\\products\\listing.steps.ts:7"
            },
            "result": {
              "status": "passed",
              "duration": 473629700
            }
          },
          {
            "arguments": [],
            "keyword": "Then ",
            "line": 7,
            "name": "I should see at least one product",
            "match": {
              "location": "src\\steps\\products\\listing.steps.ts:15"
            },
            "result": {
              "status": "passed",
              "duration": 14805299
            }
          },
          {
            "keyword": "After",
            "hidden": true,
            "result": {
              "status": "passed",
              "duration": 12072799
            }
          }
        ],
        "tags": [
          {
            "name": "@loggedin",
            "line": 1
          }
        ],
        "type": "scenario"
      }
    ],
    "id": "getting-products-count-functionality",
    "line": 3,
    "keyword": "Feature",
    "name": "Getting products count functionality",
    "tags": [
      {
        "name": "@loggedin",
        "line": 1
      }
    ],
    "uri": "src\\features\\products\\listing.feature"
  }
]